iii/verilog/lab_09/ringcounter.v
/*
* active high reset, posedge clk
* 0 0 0 1
* 0 0 1 0
* 0 1 0 0
* 1 0 0 0
*/
module ringcounter(clk, rst, out);
input clk, rst;
output reg [3:0] out;
integer i;
always @ (posedge clk) begin
    if (rst) 
        out <= 4'b0001;
    else
        out <= out<<1;
end
endmodule

iii/verilog/lab_09/ringcounter_tb.v
`timescale 1ns/1ns
`include "ringcounter.v"
module ringcounter_tb;
reg clk, rst;
wire [3:0] out;
ringcounter uut(clk, rst, out);
initial begin
    $dumpfile("ringcounter_tb.vcd");
    $dumpvars(0, ringcounter_tb);
    clk = 0;
    forever #20 clk = ~clk;
end
initial begin
    rst = 1; #20;
    rst = 1; #20;
    rst = 0; #20;
    rst = 0; #20;
    rst = 0; #20;
    rst = 0; #20;
    rst = 0; #20;
    rst = 0; #20;
    rst = 1; #20;
    rst = 1; #20;
    $finish;
end
endmodule

sem_3/verilog/lab_09/ringcounter_tb.vcd
$date
	Fri Nov  3 11:23:25 2023
$end
$version
	Icarus Verilog
$end
$timescale
	1ns
$end
$scope module ringcounter_tb $end
$var wire 4 ! out [3:0] $end
$var reg 1 " clk $end
$var reg 1 # rst $end
$scope module uut $end
$var wire 1 " clk $end
$var wire 1 # rst $end
$var reg 4 $ out [3:0] $end
$upscope $end
$upscope $end
$enddefinitions $end
$comment Show the parameter values. $end
$dumpall
$end
#0
$dumpvars
bx $
1#
0"
bx !
$end
#20
b1 !
b1 $
1"
#40
0#
0"
#60
b10 !
b10 $
1"
#80
0"
#100
b100 !
b100 $
1"
#120
0"
#140
b1000 !
b1000 $
1"
#160
1#
0"
#180
b1 !
b1 $
1"
