sem_3/verilog/lab_02/func.v
module func(f, a, b, c, d);
input a, b, c, d;
output f;
wire i1, i2;
assign i1 = c^d;
assign i2 = ~i1;
assign f = (a&i1) | (b&i2);
endmodule

iii/verilog/lab_02/func_tb.v
`timescale 1ns/1ns
`include "func.v"
module func_tb;
reg a, b, c, d;
wire f;
integer i;
func uut(f, a, b, c, d);
initial begin
    $dumpfile("func_tb.vcd");
    $dumpvars(0, func_tb);
    for (i = 0; i < 16; i = i + 1) begin
        {a, b, c, d} = i;
        #20;
    end
    $display("test complete");
end
endmodule

III/verilog/lab_02/func_tb.vcd
$date
	Sat Aug 26 13:26:48 2023
$end
$version
	Icarus Verilog
$end
$timescale
	1ns
$end
$scope module func_tb $end
$var wire 1 ! f $end
$var reg 1 " a $end
$var reg 1 # b $end
$var reg 1 $ c $end
$var reg 1 % d $end
$var integer 32 & i [31:0] $end
$scope module uut $end
$var wire 1 " a $end
$var wire 1 # b $end
$var wire 1 $ c $end
$var wire 1 % d $end
$var wire 1 ! f $end
$var wire 1 ' i1 $end
$var wire 1 ( i2 $end
$upscope $end
$upscope $end
$enddefinitions $end
$comment Show the parameter values. $end
$dumpall
$end
#0
$dumpvars
1(
0'
b0 &
0%
0$
0#
0"
0!
$end
#20
0(
1'
1%
b1 &
#40
1$
0%
b10 &
#60
1(
0'
1%
b11 &
#80
1!
1#
0$
0%
b100 &
#100
0!
0(
1'
1%
b101 &
#120
1$
0%
b110 &
#140
1!
1(
0'
1%
b111 &
#160
0!
1"
0#
0$
0%
b1000 &
#180
1!
0(
1'
1%
b1001 &
#200
1$
0%
b1010 &
#220
0!
1(
0'
1%
b1011 &
#240
1!
1#
0$
0%
b1100 &
#260
0(
1'
1%
b1101 &
#280
1$
0%
b1110 &
#300
1!
1(
0'
1%
b1111 &
#320
b10000 &
