iii/verilog/lab_01/k1.v
module k1(f, a, b, c, d);
input a, b, c, d;
output f;
assign f = c|(a&d);
endmodule;

III/verilog/lab_01/k1_tb.v
`timescale 1ns/1ns
`include "k1.v"
module k1_tb;
reg a, b, c, d;
wire f;
k1 uut(f, a, b, c, d);
initial begin
    $dumpfile("k1_tb.vcd");
    $dumpvars(0, k1_tb);
    a=0; b=0; c=0; d=0; #20;
    a=0; b=0; c=0; d=1; #20;
    a=0; b=0; c=1; d=0; #20;
    a=0; b=0; c=1; d=1; #20;
    a=0; b=1; c=0; d=0; #20;
    a=0; b=1; c=0; d=1; #20;
    a=0; b=1; c=1; d=0; #20;
    a=0; b=1; c=1; d=1; #20;
    a=1; b=0; c=0; d=0; #20;
    a=1; b=0; c=0; d=1; #20;
    a=1; b=0; c=1; d=0; #20;
    a=1; b=0; c=1; d=1; #20;
    a=1; b=1; c=0; d=0; #20;
    a=1; b=1; c=0; d=1; #20;
    a=1; b=1; c=1; d=0; #20;
    a=1; b=1; c=1; d=1; #20;
    $display("Test Complete");
end
endmodule

iii/verilog/lab_01/k1_tb.vcd
$date
	Mon Oct  2 07:08:11 2023
$end
$version
	Icarus Verilog
$end
$timescale
	1ns
$end
$scope module k1_tb $end
$var wire 1 ! f $end
$var reg 1 " a $end
$var reg 1 # b $end
$var reg 1 $ c $end
$var reg 1 % d $end
$scope module uut $end
$var wire 1 " a $end
$var wire 1 # b $end
$var wire 1 $ c $end
$var wire 1 % d $end
$var wire 1 ! f $end
$upscope $end
$upscope $end
$enddefinitions $end
$comment Show the parameter values. $end
$dumpall
$end
#0
$dumpvars
0%
0$
0#
0"
0!
$end
#20
1%
#40
1!
0%
1$
#60
1%
#80
0!
0%
0$
1#
#100
1%
#120
1!
0%
1$
#140
1%
#160
0!
0%
0$
0#
1"
#180
1!
1%
#200
0%
1$
#220
1%
#240
0!
0%
0$
1#
#260
1!
1%
#280
0%
1$
#300
1%
