III/verilog/lab_01/k3.v
module k3(f, a, b, c, d);
input a, b, c, d;
output f;
assign f = (c|d)&(c|b)&(~a|~b|~c|~d);
endmodule;

sem_3/verilog/lab_01/k3_tb.v
`timescale 1ns/1ns
`include "k3.v"
module k3_tb;
reg a, b, c, d;
wire f;
k3 uut(f, a, b, c, d);
initial begin
    $dumpfile("k3_tb.vcd");
    $dumpvars(0, k3_tb);
    a=0; b=0; c=0; d=0; #20;
    a=0; b=0; c=0; d=1; #20;
    a=0; b=0; c=1; d=0; #20;
    a=0; b=0; c=1; d=1; #20;
    a=0; b=1; c=0; d=0; #20;
    a=0; b=1; c=0; d=1; #20;
    a=0; b=1; c=1; d=0; #20;
    a=0; b=1; c=1; d=1; #20;
    a=1; b=0; c=0; d=0; #20;
    a=1; b=0; c=0; d=1; #20;
    a=1; b=0; c=1; d=0; #20;
    a=1; b=0; c=1; d=1; #20;
    a=1; b=1; c=0; d=0; #20;
    a=1; b=1; c=0; d=1; #20;
    a=1; b=1; c=1; d=0; #20;
    a=1; b=1; c=1; d=1; #20;
    $display("Test Complete");
end
endmodule

III/verilog/lab_01/k3_tb.vcd
$date
	Sat Aug 12 06:47:20 2023
$end
$version
	Icarus Verilog
$end
$timescale
	1ns
$end
$scope module k3_tb $end
$var wire 1 ! f $end
$var reg 1 " a $end
$var reg 1 # b $end
$var reg 1 $ c $end
$var reg 1 % d $end
$scope module uut $end
$var wire 1 " a $end
$var wire 1 # b $end
$var wire 1 $ c $end
$var wire 1 % d $end
$var wire 1 ! f $end
$upscope $end
$upscope $end
$enddefinitions $end
$comment Show the parameter values. $end
$dumpall
$end
#0
$dumpvars
0%
0$
0#
0"
0!
$end
#20
1%
#40
1!
0%
1$
#60
1%
#80
0!
0%
0$
1#
#100
1!
1%
#120
0%
1$
#140
1%
#160
0!
0%
0$
0#
1"
#180
1%
#200
1!
0%
1$
#220
1%
#240
0!
0%
0$
1#
#260
1!
1%
#280
0%
1$
#300
0!
1%
