iii/verilog/lab_01/k4.v
module k4(f, a, b, c, d);
input a, b, c, d;
output f;
assign f = (~c|d)&(a|~b|c|~d)&(~a|b|c);
endmodule;

sem_3/verilog/lab_01/k4_tb.v
`timescale 1ns/1ns
`include "k4.v"
module k4_tb;
reg a, b, c, d;
wire f;
k4 uut(f, a, b, c, d);
initial begin
    $dumpfile("k4_tb.vcd");
    $dumpvars(0, k4_tb);
    a=0; b=0; c=0; d=0; #20;
    a=0; b=0; c=0; d=1; #20;
    a=0; b=0; c=1; d=0; #20;
    a=0; b=0; c=1; d=1; #20;
    a=0; b=1; c=0; d=0; #20;
    a=0; b=1; c=0; d=1; #20;
    a=0; b=1; c=1; d=0; #20;
    a=0; b=1; c=1; d=1; #20;
    a=1; b=0; c=0; d=0; #20;
    a=1; b=0; c=0; d=1; #20;
    a=1; b=0; c=1; d=0; #20;
    a=1; b=0; c=1; d=1; #20;
    a=1; b=1; c=0; d=0; #20;
    a=1; b=1; c=0; d=1; #20;
    a=1; b=1; c=1; d=0; #20;
    a=1; b=1; c=1; d=1; #20;
    $display("Test Complete");
end
endmodule

III/verilog/lab_01/k4_tb.vcd
$date
	Sat Aug 12 06:52:15 2023
$end
$version
	Icarus Verilog
$end
$timescale
	1ns
$end
$scope module k4_tb $end
$var wire 1 ! f $end
$var reg 1 " a $end
$var reg 1 # b $end
$var reg 1 $ c $end
$var reg 1 % d $end
$scope module uut $end
$var wire 1 " a $end
$var wire 1 # b $end
$var wire 1 $ c $end
$var wire 1 % d $end
$var wire 1 ! f $end
$upscope $end
$upscope $end
$enddefinitions $end
$comment Show the parameter values. $end
$dumpall
$end
#0
$dumpvars
0%
0$
0#
0"
1!
$end
#20
1%
#40
0!
0%
1$
#60
1!
1%
#80
0%
0$
1#
#100
0!
1%
#120
0%
1$
#140
1!
1%
#160
0!
0%
0$
0#
1"
#180
1%
#200
0!
0%
1$
#220
1!
1%
#240
0%
0$
1#
#260
1%
#280
0!
0%
1$
#300
1!
1%
