iii/verilog/lab_07/regn.v
module regn(I, clk, A);
parameter n = 8;
input [n - 1:0] I;
input clk;
output reg [n - 1: 0] A;
always @ (posedge clk) begin
    A <= I;
end
endmodule

iii/verilog/lab_07/regn_tb.v
`timescale 1ns/1ns
`include "regn.v"
module regn_tb;
reg [7:0] I;
reg clk;
wire [7:0] A; 
integer i;
regn uut(I, clk, A);
parameter timeout = 500;
initial begin
    $dumpfile("regn_tb.vcd");
    $dumpvars(0, regn_tb);
    clk = 0; 
    forever #20 clk = ~clk;
end
initial begin
    for (i = 0; i < 256; i = i + 1) begin
        I = i; #20;
    end
    #(timeout) $finish;
end
endmodule

sem_3/verilog/lab_07/regn_tb.vcd
$date
	Fri Oct 27 10:09:41 2023
$end
$version
	Icarus Verilog
$end
$timescale
	1ns
$end
$scope module regn_tb $end
$var wire 8 ! A [7:0] $end
$var parameter 32 " timeout $end
$var reg 8 # I [7:0] $end
$var reg 1 $ clk $end
$var integer 32 % i [31:0] $end
$scope module uut $end
$var wire 8 & I [7:0] $end
$var wire 1 $ clk $end
$var parameter 32 ' n $end
$var reg 8 ( A [7:0] $end
$upscope $end
$upscope $end
$enddefinitions $end
$comment Show the parameter values. $end
$dumpall
b1000 '
b111110100 "
$end
#0
$dumpvars
bx (
b0 &
b0 %
0$
b0 #
bx !
$end
#20
b1 !
b1 (
b1 #
b1 &
b1 %
1$
#40
b10 #
b10 &
b10 %
0$
#60
b11 !
b11 (
b11 #
b11 &
b11 %
1$
#80
b100 #
b100 &
b100 %
0$
#100
b101 !
b101 (
b101 #
b101 &
b101 %
1$
#120
b110 #
b110 &
b110 %
0$
#140
b111 !
b111 (
b111 #
b111 &
b111 %
1$
#160
b1000 #
b1000 &
b1000 %
0$
#180
b1001 !
b1001 (
b1001 #
b1001 &
b1001 %
1$
#200
b1010 #
b1010 &
b1010 %
0$
#220
b1011 !
b1011 (
b1011 #
b1011 &
b1011 %
1$
#240
b1100 #
b1100 &
b1100 %
0$
#260
b1101 !
b1101 (
b1101 #
b1101 &
b1101 %
1$
#280
b1110 #
b1110 &
b1110 %
0$
#300
b1111 !
b1111 (
b1111 #
b1111 &
b1111 %
1$
#320
b10000 #
b10000 &
b10000 %
0$
#340
b10001 !
b10001 (
b10001 #
b10001 &
b10001 %
1$
#360
b10010 #
b10010 &
b10010 %
0$
#380
b10011 !
b10011 (
b10011 #
b10011 &
b10011 %
1$
#400
b10100 #
b10100 &
b10100 %
0$
#420
b10101 !
b10101 (
b10101 #
b10101 &
b10101 %
1$
#440
b10110 #
b10110 &
b10110 %
0$
#460
b10111 !
b10111 (
b10111 #
b10111 &
b10111 %
1$
#480
b11000 #
b11000 &
b11000 %
0$
#500
b11001 !
b11001 (
b11001 #
b11001 &
b11001 %
1$
#520
b11010 #
b11010 &
b11010 %
0$
#540
b11011 !
b11011 (
b11011 #
b11011 &
b11011 %
1$
#560
b11100 #
b11100 &
b11100 %
0$
#580
b11101 !
b11101 (
b11101 #
b11101 &
b11101 %
1$
#600
b11110 #
b11110 &
b11110 %
0$
#620
b11111 !
b11111 (
b11111 #
b11111 &
b11111 %
1$
#640
b100000 #
b100000 &
b100000 %
0$
#660
b100001 !
b100001 (
b100001 #
b100001 &
b100001 %
1$
#680
b100010 #
b100010 &
b100010 %
0$
#700
b100011 !
b100011 (
b100011 #
b100011 &
b100011 %
1$
#720
b100100 #
b100100 &
b100100 %
0$
#740
b100101 !
b100101 (
b100101 #
b100101 &
b100101 %
1$
#760
b100110 #
b100110 &
b100110 %
0$
#780
b100111 !
b100111 (
b100111 #
b100111 &
b100111 %
1$
#800
b101000 #
b101000 &
b101000 %
0$
#820
b101001 !
b101001 (
b101001 #
b101001 &
b101001 %
1$
#840
b101010 #
b101010 &
b101010 %
0$
#860
b101011 !
b101011 (
b101011 #
b101011 &
b101011 %
1$
#880
b101100 #
b101100 &
b101100 %
0$
#900
b101101 !
b101101 (
b101101 #
b101101 &
b101101 %
1$
#920
b101110 #
b101110 &
b101110 %
0$
#940
b101111 !
b101111 (
b101111 #
b101111 &
b101111 %
1$
#960
b110000 #
b110000 &
b110000 %
0$
#980
b110001 !
b110001 (
b110001 #
b110001 &
b110001 %
1$
#1000
b110010 #
b110010 &
b110010 %
0$
#1020
b110011 !
b110011 (
b110011 #
b110011 &
b110011 %
1$
#1040
b110100 #
b110100 &
b110100 %
0$
#1060
b110101 !
b110101 (
b110101 #
b110101 &
b110101 %
1$
#1080
b110110 #
b110110 &
b110110 %
0$
#1100
b110111 !
b110111 (
b110111 #
b110111 &
b110111 %
1$
#1120
b111000 #
b111000 &
b111000 %
0$
#1140
b111001 !
b111001 (
b111001 #
b111001 &
b111001 %
1$
#1160
b111010 #
b111010 &
b111010 %
0$
#1180
b111011 !
b111011 (
b111011 #
b111011 &
b111011 %
1$
#1200
b111100 #
b111100 &
b111100 %
0$
#1220
b111101 !
b111101 (
b111101 #
b111101 &
b111101 %
1$
#1240
b111110 #
b111110 &
b111110 %
0$
#1260
b111111 !
b111111 (
b111111 #
b111111 &
b111111 %
1$
#1280
b1000000 #
b1000000 &
b1000000 %
0$
#1300
b1000001 !
b1000001 (
b1000001 #
b1000001 &
b1000001 %
1$
#1320
b1000010 #
b1000010 &
b1000010 %
0$
#1340
b1000011 !
b1000011 (
b1000011 #
b1000011 &
b1000011 %
1$
#1360
b1000100 #
b1000100 &
b1000100 %
0$
#1380
b1000101 !
b1000101 (
b1000101 #
b1000101 &
b1000101 %
1$
#1400
b1000110 #
b1000110 &
b1000110 %
0$
#1420
b1000111 !
b1000111 (
b1000111 #
b1000111 &
b1000111 %
1$
#1440
b1001000 #
b1001000 &
b1001000 %
0$
#1460
b1001001 !
b1001001 (
b1001001 #
b1001001 &
b1001001 %
1$
#1480
b1001010 #
b1001010 &
b1001010 %
0$
#1500
b1001011 !
b1001011 (
b1001011 #
b1001011 &
b1001011 %
1$
#1520
b1001100 #
b1001100 &
b1001100 %
0$
#1540
b1001101 !
b1001101 (
b1001101 #
b1001101 &
b1001101 %
1$
#1560
b1001110 #
b1001110 &
b1001110 %
0$
#1580
b1001111 !
b1001111 (
b1001111 #
b1001111 &
b1001111 %
1$
#1600
b1010000 #
b1010000 &
b1010000 %
0$
#1620
b1010001 !
b1010001 (
b1010001 #
b1010001 &
b1010001 %
1$
#1640
b1010010 #
b1010010 &
b1010010 %
0$
#1660
b1010011 !
b1010011 (
b1010011 #
b1010011 &
b1010011 %
1$
#1680
b1010100 #
b1010100 &
b1010100 %
0$
#1700
b1010101 !
b1010101 (
b1010101 #
b1010101 &
b1010101 %
1$
#1720
b1010110 #
b1010110 &
b1010110 %
0$
#1740
b1010111 !
b1010111 (
b1010111 #
b1010111 &
b1010111 %
1$
#1760
b1011000 #
b1011000 &
b1011000 %
0$
#1780
b1011001 !
b1011001 (
b1011001 #
b1011001 &
b1011001 %
1$
#1800
b1011010 #
b1011010 &
b1011010 %
0$
#1820
b1011011 !
b1011011 (
b1011011 #
b1011011 &
b1011011 %
1$
#1840
b1011100 #
b1011100 &
b1011100 %
0$
#1860
b1011101 !
b1011101 (
b1011101 #
b1011101 &
b1011101 %
1$
#1880
b1011110 #
b1011110 &
b1011110 %
0$
#1900
b1011111 !
b1011111 (
b1011111 #
b1011111 &
b1011111 %
1$
#1920
b1100000 #
b1100000 &
b1100000 %
0$
#1940
b1100001 !
b1100001 (
b1100001 #
b1100001 &
b1100001 %
1$
#1960
b1100010 #
b1100010 &
b1100010 %
0$
#1980
b1100011 !
b1100011 (
b1100011 #
b1100011 &
b1100011 %
1$
#2000
b1100100 #
b1100100 &
b1100100 %
0$
#2020
b1100101 !
b1100101 (
b1100101 #
b1100101 &
b1100101 %
1$
#2040
b1100110 #
b1100110 &
b1100110 %
0$
#2060
b1100111 !
b1100111 (
b1100111 #
b1100111 &
b1100111 %
1$
#2080
b1101000 #
b1101000 &
b1101000 %
0$
#2100
b1101001 !
b1101001 (
b1101001 #
b1101001 &
b1101001 %
1$
#2120
b1101010 #
b1101010 &
b1101010 %
0$
#2140
b1101011 !
b1101011 (
b1101011 #
b1101011 &
b1101011 %
1$
#2160
b1101100 #
b1101100 &
b1101100 %
0$
#2180
b1101101 !
b1101101 (
b1101101 #
b1101101 &
b1101101 %
1$
#2200
b1101110 #
b1101110 &
b1101110 %
0$
#2220
b1101111 !
b1101111 (
b1101111 #
b1101111 &
b1101111 %
1$
#2240
b1110000 #
b1110000 &
b1110000 %
0$
#2260
b1110001 !
b1110001 (
b1110001 #
b1110001 &
b1110001 %
1$
#2280
b1110010 #
b1110010 &
b1110010 %
0$
#2300
b1110011 !
b1110011 (
b1110011 #
b1110011 &
b1110011 %
1$
#2320
b1110100 #
b1110100 &
b1110100 %
0$
#2340
b1110101 !
b1110101 (
b1110101 #
b1110101 &
b1110101 %
1$
#2360
b1110110 #
b1110110 &
b1110110 %
0$
#2380
b1110111 !
b1110111 (
b1110111 #
b1110111 &
b1110111 %
1$
#2400
b1111000 #
b1111000 &
b1111000 %
0$
#2420
b1111001 !
b1111001 (
b1111001 #
b1111001 &
b1111001 %
1$
#2440
b1111010 #
b1111010 &
b1111010 %
0$
#2460
b1111011 !
b1111011 (
b1111011 #
b1111011 &
b1111011 %
1$
#2480
b1111100 #
b1111100 &
b1111100 %
0$
#2500
b1111101 !
b1111101 (
b1111101 #
b1111101 &
b1111101 %
1$
#2520
b1111110 #
b1111110 &
b1111110 %
0$
#2540
b1111111 !
b1111111 (
b1111111 #
b1111111 &
b1111111 %
1$
#2560
b10000000 #
b10000000 &
b10000000 %
0$
#2580
b10000001 !
b10000001 (
b10000001 #
b10000001 &
b10000001 %
1$
#2600
b10000010 #
b10000010 &
b10000010 %
0$
#2620
b10000011 !
b10000011 (
b10000011 #
b10000011 &
b10000011 %
1$
#2640
b10000100 #
b10000100 &
b10000100 %
0$
#2660
b10000101 !
b10000101 (
b10000101 #
b10000101 &
b10000101 %
1$
#2680
b10000110 #
b10000110 &
b10000110 %
0$
#2700
b10000111 !
b10000111 (
b10000111 #
b10000111 &
b10000111 %
1$
#2720
b10001000 #
b10001000 &
b10001000 %
0$
#2740
b10001001 !
b10001001 (
b10001001 #
b10001001 &
b10001001 %
1$
#2760
b10001010 #
b10001010 &
b10001010 %
0$
#2780
b10001011 !
b10001011 (
b10001011 #
b10001011 &
b10001011 %
1$
#2800
b10001100 #
b10001100 &
b10001100 %
0$
#2820
b10001101 !
b10001101 (
b10001101 #
b10001101 &
b10001101 %
1$
#2840
b10001110 #
b10001110 &
b10001110 %
0$
#2860
b10001111 !
b10001111 (
b10001111 #
b10001111 &
b10001111 %
1$
#2880
b10010000 #
b10010000 &
b10010000 %
0$
#2900
b10010001 !
b10010001 (
b10010001 #
b10010001 &
b10010001 %
1$
#2920
b10010010 #
b10010010 &
b10010010 %
0$
#2940
b10010011 !
b10010011 (
b10010011 #
b10010011 &
b10010011 %
1$
#2960
b10010100 #
b10010100 &
b10010100 %
0$
#2980
b10010101 !
b10010101 (
b10010101 #
b10010101 &
b10010101 %
1$
#3000
b10010110 #
b10010110 &
b10010110 %
0$
#3020
b10010111 !
b10010111 (
b10010111 #
b10010111 &
b10010111 %
1$
#3040
b10011000 #
b10011000 &
b10011000 %
0$
#3060
b10011001 !
b10011001 (
b10011001 #
b10011001 &
b10011001 %
1$
#3080
b10011010 #
b10011010 &
b10011010 %
0$
#3100
b10011011 !
b10011011 (
b10011011 #
b10011011 &
b10011011 %
1$
#3120
b10011100 #
b10011100 &
b10011100 %
0$
#3140
b10011101 !
b10011101 (
b10011101 #
b10011101 &
b10011101 %
1$
#3160
b10011110 #
b10011110 &
b10011110 %
0$
#3180
b10011111 !
b10011111 (
b10011111 #
b10011111 &
b10011111 %
1$
#3200
b10100000 #
b10100000 &
b10100000 %
0$
#3220
b10100001 !
b10100001 (
b10100001 #
b10100001 &
b10100001 %
1$
#3240
b10100010 #
b10100010 &
b10100010 %
0$
#3260
b10100011 !
b10100011 (
b10100011 #
b10100011 &
b10100011 %
1$
#3280
b10100100 #
b10100100 &
b10100100 %
0$
#3300
b10100101 !
b10100101 (
b10100101 #
b10100101 &
b10100101 %
1$
#3320
b10100110 #
b10100110 &
b10100110 %
0$
#3340
b10100111 !
b10100111 (
b10100111 #
b10100111 &
b10100111 %
1$
#3360
b10101000 #
b10101000 &
b10101000 %
0$
#3380
b10101001 !
b10101001 (
b10101001 #
b10101001 &
b10101001 %
1$
#3400
b10101010 #
b10101010 &
b10101010 %
0$
#3420
b10101011 !
b10101011 (
b10101011 #
b10101011 &
b10101011 %
1$
#3440
b10101100 #
b10101100 &
b10101100 %
0$
#3460
b10101101 !
b10101101 (
b10101101 #
b10101101 &
b10101101 %
1$
#3480
b10101110 #
b10101110 &
b10101110 %
0$
#3500
b10101111 !
b10101111 (
b10101111 #
b10101111 &
b10101111 %
1$
#3520
b10110000 #
b10110000 &
b10110000 %
0$
#3540
b10110001 !
b10110001 (
b10110001 #
b10110001 &
b10110001 %
1$
#3560
b10110010 #
b10110010 &
b10110010 %
0$
#3580
b10110011 !
b10110011 (
b10110011 #
b10110011 &
b10110011 %
1$
#3600
b10110100 #
b10110100 &
b10110100 %
0$
#3620
b10110101 !
b10110101 (
b10110101 #
b10110101 &
b10110101 %
1$
#3640
b10110110 #
b10110110 &
b10110110 %
0$
#3660
b10110111 !
b10110111 (
b10110111 #
b10110111 &
b10110111 %
1$
#3680
b10111000 #
b10111000 &
b10111000 %
0$
#3700
b10111001 !
b10111001 (
b10111001 #
b10111001 &
b10111001 %
1$
#3720
b10111010 #
b10111010 &
b10111010 %
0$
#3740
b10111011 !
b10111011 (
b10111011 #
b10111011 &
b10111011 %
1$
#3760
b10111100 #
b10111100 &
b10111100 %
0$
#3780
b10111101 !
b10111101 (
b10111101 #
b10111101 &
b10111101 %
1$
#3800
b10111110 #
b10111110 &
b10111110 %
0$
#3820
b10111111 !
b10111111 (
b10111111 #
b10111111 &
b10111111 %
1$
#3840
b11000000 #
b11000000 &
b11000000 %
0$
#3860
b11000001 !
b11000001 (
b11000001 #
b11000001 &
b11000001 %
1$
#3880
b11000010 #
b11000010 &
b11000010 %
0$
#3900
b11000011 !
b11000011 (
b11000011 #
b11000011 &
b11000011 %
1$
#3920
b11000100 #
b11000100 &
b11000100 %
0$
#3940
b11000101 !
b11000101 (
b11000101 #
b11000101 &
b11000101 %
1$
#3960
b11000110 #
b11000110 &
b11000110 %
0$
#3980
b11000111 !
b11000111 (
b11000111 #
b11000111 &
b11000111 %
1$
#4000
b11001000 #
b11001000 &
b11001000 %
0$
#4020
b11001001 !
b11001001 (
b11001001 #
b11001001 &
b11001001 %
1$
#4040
b11001010 #
b11001010 &
b11001010 %
0$
#4060
b11001011 !
b11001011 (
b11001011 #
b11001011 &
b11001011 %
1$
#4080
b11001100 #
b11001100 &
b11001100 %
0$
#4100
b11001101 !
b11001101 (
b11001101 #
b11001101 &
b11001101 %
1$
#4120
b11001110 #
b11001110 &
b11001110 %
0$
#4140
b11001111 !
b11001111 (
b11001111 #
b11001111 &
b11001111 %
1$
#4160
b11010000 #
b11010000 &
b11010000 %
0$
#4180
b11010001 !
b11010001 (
b11010001 #
b11010001 &
b11010001 %
1$
#4200
b11010010 #
b11010010 &
b11010010 %
0$
#4220
b11010011 !
b11010011 (
b11010011 #
b11010011 &
b11010011 %
1$
#4240
b11010100 #
b11010100 &
b11010100 %
0$
#4260
b11010101 !
b11010101 (
b11010101 #
b11010101 &
b11010101 %
1$
#4280
b11010110 #
b11010110 &
b11010110 %
0$
#4300
b11010111 !
b11010111 (
b11010111 #
b11010111 &
b11010111 %
1$
#4320
b11011000 #
b11011000 &
b11011000 %
0$
#4340
b11011001 !
b11011001 (
b11011001 #
b11011001 &
b11011001 %
1$
#4360
b11011010 #
b11011010 &
b11011010 %
0$
#4380
b11011011 !
b11011011 (
b11011011 #
b11011011 &
b11011011 %
1$
#4400
b11011100 #
b11011100 &
b11011100 %
0$
#4420
b11011101 !
b11011101 (
b11011101 #
b11011101 &
b11011101 %
1$
#4440
b11011110 #
b11011110 &
b11011110 %
0$
#4460
b11011111 !
b11011111 (
b11011111 #
b11011111 &
b11011111 %
1$
#4480
b11100000 #
b11100000 &
b11100000 %
0$
#4500
b11100001 !
b11100001 (
b11100001 #
b11100001 &
b11100001 %
1$
#4520
b11100010 #
b11100010 &
b11100010 %
0$
#4540
b11100011 !
b11100011 (
b11100011 #
b11100011 &
b11100011 %
1$
#4560
b11100100 #
b11100100 &
b11100100 %
0$
#4580
b11100101 !
b11100101 (
b11100101 #
b11100101 &
b11100101 %
1$
#4600
b11100110 #
b11100110 &
b11100110 %
0$
#4620
b11100111 !
b11100111 (
b11100111 #
b11100111 &
b11100111 %
1$
#4640
b11101000 #
b11101000 &
b11101000 %
0$
#4660
b11101001 !
b11101001 (
b11101001 #
b11101001 &
b11101001 %
1$
#4680
b11101010 #
b11101010 &
b11101010 %
0$
#4700
b11101011 !
b11101011 (
b11101011 #
b11101011 &
b11101011 %
1$
#4720
b11101100 #
b11101100 &
b11101100 %
0$
#4740
b11101101 !
b11101101 (
b11101101 #
b11101101 &
b11101101 %
1$
#4760
b11101110 #
b11101110 &
b11101110 %
0$
#4780
b11101111 !
b11101111 (
b11101111 #
b11101111 &
b11101111 %
1$
#4800
b11110000 #
b11110000 &
b11110000 %
0$
#4820
b11110001 !
b11110001 (
b11110001 #
b11110001 &
b11110001 %
1$
#4840
b11110010 #
b11110010 &
b11110010 %
0$
#4860
b11110011 !
b11110011 (
b11110011 #
b11110011 &
b11110011 %
1$
#4880
b11110100 #
b11110100 &
b11110100 %
0$
#4900
b11110101 !
b11110101 (
b11110101 #
b11110101 &
b11110101 %
1$
#4920
b11110110 #
b11110110 &
b11110110 %
0$
#4940
b11110111 !
b11110111 (
b11110111 #
b11110111 &
b11110111 %
1$
#4960
b11111000 #
b11111000 &
b11111000 %
0$
#4980
b11111001 !
b11111001 (
b11111001 #
b11111001 &
b11111001 %
1$
#5000
b11111010 #
b11111010 &
b11111010 %
0$
#5020
b11111011 !
b11111011 (
b11111011 #
b11111011 &
b11111011 %
1$
#5040
b11111100 #
b11111100 &
b11111100 %
0$
#5060
b11111101 !
b11111101 (
b11111101 #
b11111101 &
b11111101 %
1$
#5080
b11111110 #
b11111110 &
b11111110 %
0$
#5100
b11111111 !
b11111111 (
b11111111 #
b11111111 &
b11111111 %
1$
#5120
b100000000 %
0$
