iii/verilog/lab_03/mux16to1.v
module mux16to1(w, s, f);
input [15:0] w;
input [3:0] s;
output f;
wire[1:0] m;
mux8to1 m1(w[7:0], s[2:0], m[0]);
mux8to1 m2(w[15:8], s[2:0], m[1]);
mux2to1 m3(m[1:0], s[3], f);
endmodule

module mux8to1(w, s, f);
input[7:0] w;
input[2:0] s;
output reg f;
always @ (w or s)
begin
    case (s)
         0:f = w[0];
         1:f = w[1];
         2:f = w[2];
         3:f = w[3];
         4:f = w[4];
         5:f = w[5];
         6:f = w[6];
         7:f = w[7];
     endcase
end
endmodule

module mux2to1(w, s, f);
input[1:0] w;
input s;
output reg f;
always @ (w or s)
begin
    case (s)
        0: f = w[0];
        1: f = w[1];
    endcase
end
endmodule

sem_3/verilog/lab_03/mux16to1_tb.v
`timescale 1ns/1ns
`include "mux16to1.v"
module mux16to1_tb;
reg[15:0] w;
reg[3:0] s;
wire f;
integer i;
mux16to1 uut(w, s, f);
initial begin
    $dumpfile("mux16to1_tb.vcd");
    $dumpvars(0, mux16to1_tb);
    for (i = 0; i < 15; i = i + 1) begin
        w = 65280; s = i; #20;
    end
end
endmodule

III/verilog/lab_03/mux16to1_tb.vcd
$date
	Sat Sep  2 03:43:29 2023
$end
$version
	Icarus Verilog
$end
$timescale
	1ns
$end
$scope module mux16to1_tb $end
$var wire 1 ! f $end
$var reg 4 " s [3:0] $end
$var reg 16 # w [15:0] $end
$var integer 32 $ i [31:0] $end
$scope module uut $end
$var wire 4 % s [3:0] $end
$var wire 16 & w [15:0] $end
$var wire 2 ' m [1:0] $end
$var wire 1 ! f $end
$scope module m1 $end
$var wire 3 ( s [2:0] $end
$var wire 8 ) w [7:0] $end
$var reg 1 * f $end
$upscope $end
$scope module m2 $end
$var wire 3 + s [2:0] $end
$var wire 8 , w [7:0] $end
$var reg 1 - f $end
$upscope $end
$scope module m3 $end
$var wire 1 . s $end
$var wire 2 / w [1:0] $end
$var reg 1 ! f $end
$upscope $end
$upscope $end
$upscope $end
$enddefinitions $end
$comment Show the parameter values. $end
$dumpall
$end
#0
$dumpvars
b10 /
0.
1-
b11111111 ,
b0 +
0*
b0 )
b0 (
b10 '
b1111111100000000 &
b0 %
b0 $
b1111111100000000 #
b0 "
0!
$end
#20
b1 (
b1 +
b1 "
b1 %
b1 $
#40
b10 (
b10 +
b10 "
b10 %
b10 $
#60
b11 (
b11 +
b11 "
b11 %
b11 $
#80
b100 (
b100 +
b100 "
b100 %
b100 $
#100
b101 (
b101 +
b101 "
b101 %
b101 $
#120
b110 (
b110 +
b110 "
b110 %
b110 $
#140
b111 (
b111 +
b111 "
b111 %
b111 $
#160
1!
b0 (
b0 +
1.
b1000 "
b1000 %
b1000 $
#180
b1 (
b1 +
b1001 "
b1001 %
b1001 $
#200
b10 (
b10 +
b1010 "
b1010 %
b1010 $
#220
b11 (
b11 +
b1011 "
b1011 %
b1011 $
#240
b100 (
b100 +
b1100 "
b1100 %
b1100 $
#260
b101 (
b101 +
b1101 "
b1101 %
b1101 $
#280
b110 (
b110 +
b1110 "
b1110 %
b1110 $
#300
b1111 $
