iii/verilog/lab_04/decoder2to4.v
module decoder2to4(en, s, y);
input en;
input [1:0] s;
output reg [3:0] y;
integer i;
always @ (en or s) begin
    y = 4'b0;
    if (en) begin
        for(i=0;i<4;i=i+1) begin
            if(s == i) begin
                y[i] = 1'b1;
            end
        end
    end
    else 
        y=4'b0;
end
endmodule

iii/verilog/lab_04/decoder2to4_tb.v
`timescale 1ns/1ns
`include "decoder2to4.v"
module decoder2to4_tb;
reg en;
reg [1:0] s;
wire [3:0] y;
integer i, j;
decoder2to4 uut(en, s, y);
initial begin
    $dumpfile("decoder2to4_tb.vcd");
    $dumpvars(0, decoder2to4_tb);
    for (i = 0; i < 2; i = i + 1) begin
        for (j = 0; j < 4; j = j + 1) begin
            en = i; s = j; #20;
        end
    end
end
endmodule

iii/verilog/lab_04/decoder2to4_tb.vcd
$date
	Sat Oct 14 10:13:48 2023
$end
$version
	Icarus Verilog
$end
$timescale
	1ns
$end
$scope module decoder2to4_tb $end
$var wire 4 ! y [3:0] $end
$var reg 1 " en $end
$var reg 2 # s [1:0] $end
$var integer 32 $ i [31:0] $end
$var integer 32 % j [31:0] $end
$scope module uut $end
$var wire 1 " en $end
$var wire 2 & s [1:0] $end
$var reg 4 ' y [3:0] $end
$var integer 32 ( i [31:0] $end
$upscope $end
$upscope $end
$enddefinitions $end
$comment Show the parameter values. $end
$dumpall
$end
#0
$dumpvars
bx (
b0 '
b0 &
b0 %
b0 $
b0 #
0"
b0 !
$end
#20
b1 #
b1 &
b1 %
#40
b10 #
b10 &
b10 %
#60
b11 #
b11 &
b11 %
#80
b1 !
b1 '
b100 (
b0 #
b0 &
1"
b1 $
b0 %
#100
b100 (
b10 !
b10 '
b1 #
b1 &
b1 %
#120
b100 (
b100 !
b100 '
b10 #
b10 &
b10 %
#140
b100 (
b1000 !
b1000 '
b11 #
b11 &
b11 %
#160
b10 $
b100 %
