iii/verilog/lab_04/pencoder4to2.v
module pencoder4to2(s, y);
input [3:0] s;
output reg [1:0] y;
always@(s)
begin 
    casex (s)
        4'b0000: y = 2'bxx;
        4'b0001: y = 2'b00;
        4'b001x: y = 2'b01;
        4'b01xx: y = 2'b10;
        4'b1xxx: y = 2'b11;
    endcase
end
endmodule

iii/verilog/lab_04/pencoder4to2_tb.v
`timescale 1ns/1ns
`include "pencoder4to2.v"
module pencoder4to2_tb;
reg en;
reg [3:0] s;
wire [1:0] y;
integer i;
pencoder4to2 uut(s, y);
initial begin
    $dumpfile("pencoder4to2_tb.vcd");
    $dumpvars(0, pencoder4to2_tb);
    for (i = 0; i < 16; i = i + 1) begin
        s = i; #20;
    end
end
endmodule

iii/verilog/lab_04/pencoder4to2_tb.vcd
$date
	Sat Sep  9 13:10:46 2023
$end
$version
	Icarus Verilog
$end
$timescale
	1ns
$end
$scope module pencoder4to2_tb $end
$var wire 2 ! y [1:0] $end
$var reg 4 " s [3:0] $end
$var integer 32 # i [31:0] $end
$scope module uut $end
$var wire 4 $ s [3:0] $end
$var reg 2 % y [1:0] $end
$upscope $end
$upscope $end
$enddefinitions $end
$comment Show the parameter values. $end
$dumpall
$end
#0
$dumpvars
bx %
b0 $
b0 #
b0 "
bx !
$end
#20
b0 !
b0 %
b1 "
b1 $
b1 #
#40
b1 !
b1 %
b10 "
b10 $
b10 #
#60
b11 "
b11 $
b11 #
#80
b10 !
b10 %
b100 "
b100 $
b100 #
#100
b101 "
b101 $
b101 #
#120
b110 "
b110 $
b110 #
#140
b111 "
b111 $
b111 #
#160
b11 !
b11 %
b1000 "
b1000 $
b1000 #
#180
b1001 "
b1001 $
b1001 #
#200
b1010 "
b1010 $
b1010 #
#220
b1011 "
b1011 $
b1011 #
#240
b1100 "
b1100 $
b1100 #
#260
b1101 "
b1101 $
b1101 #
#280
b1110 "
b1110 $
b1110 #
#300
b1111 "
b1111 $
b1111 #
#320
b10000 #
