iii/verilog/lab_09/dff.v
module dff(d, clk, rst, q);
input d, clk, rst;
output reg q;
always @ (posedge clk or posedge rst) begin
    if (rst)
        q <= 0;
    else 
        q <= d;
end
endmodule

III/verilog/lab_08/state1.v
`include "dff.v"
module state1(state, in, out, clk, rst);
input in, clk, rst;
output [2:0] state;
output out;
wire a, b, c, x;
assign a = state[2];
assign b = state[1];
assign c = state[0];
assign x = in;
dff da((~a&b&~c&~x)|(a&~b&~c&~x), clk, rst, state[2]);
dff db((~a&~b&~x)|(~a&b&x), clk, rst, state[1]);
dff dc((~a&~b&~c)|(~a&b&c&~x), clk, rst, state[0]);
assign out = (~a&b&~c&~x)|(~a&b&c)|(a&~b&~x);
endmodule

iii/verilog/lab_08/state1_tb.v
`timescale 1ns/1ns
`include "state1.v"
module state1_tb;
reg rst, in, clk;
wire [2:0] state; 
wire out;
state1 uut(state, in, out , clk, rst);
initial begin
    $dumpfile("state1_tb.vcd");
    $dumpvars(0, state1_tb);
    clk = 0; 
    forever #20 clk = ~clk;
end
initial begin
	rst = 1; in = 0; #20;
	rst = 0; in = 0; #20;
	in = 0; #20;
	in = 1; #20;
	in = 0; #20;
	in = 0; #20;
	in = 0; #20;
	in = 1; #20;
	in = 1; #20;
	in = 1; #20;
	in = 1; #20;
	$finish;
end
endmodule

iii/verilog/lab_08/state1_tb.vcd
$date
	Sat Nov  4 18:10:40 2023
$end
$version
	Icarus Verilog
$end
$timescale
	1ns
$end
$scope module state1_tb $end
$var wire 3 ! state [2:0] $end
$var wire 1 " out $end
$var reg 1 # clk $end
$var reg 1 $ in $end
$var reg 1 % rst $end
$scope module uut $end
$var wire 1 # clk $end
$var wire 1 $ in $end
$var wire 1 " out $end
$var wire 1 % rst $end
$var wire 1 & x $end
$var wire 3 ' state [2:0] $end
$var wire 1 ( c $end
$var wire 1 ) b $end
$var wire 1 * a $end
$scope module da $end
$var wire 1 # clk $end
$var wire 1 + d $end
$var wire 1 % rst $end
$var reg 1 , q $end
$upscope $end
$scope module db $end
$var wire 1 # clk $end
$var wire 1 - d $end
$var wire 1 % rst $end
$var reg 1 . q $end
$upscope $end
$scope module dc $end
$var wire 1 # clk $end
$var wire 1 / d $end
$var wire 1 % rst $end
$var reg 1 0 q $end
$upscope $end
$upscope $end
$upscope $end
$enddefinitions $end
$comment Show the parameter values. $end
$dumpall
$end
#0
$dumpvars
00
1/
0.
1-
0,
0+
0*
0)
0(
b0 '
0&
1%
0$
0#
0"
b0 !
$end
#20
0-
1"
1(
1)
10
b11 !
b11 '
1.
0%
1#
#40
0#
#60
0"
0)
b1 !
b1 '
0.
0/
0-
1&
1$
1#
#80
1-
0&
0$
0#
#100
1"
0-
1+
0(
1)
00
b10 !
b10 '
1.
1#
#120
0#
#140
1*
0)
1,
b100 !
b100 '
0.
0"
0+
0-
1&
1$
1#
#160
0#
#180
1/
0*
b0 !
b0 '
0,
1#
#200
0#
#220
0/
1(
b1 !
b1 '
10
1#
