III/verilog/lab_06/tff.v
module tff(t, clk, rst, q);
input t, clk, rst;
output reg q;
always @ (negedge clk or negedge rst) begin
    if (!rst)
        q <= 0;
    else 
        if (t)
            q <= ~q;
        else 
            q <= q;
end
endmodule

iii/verilog/lab_08/state2.v
`include "tff.v"
module state2(state, in, clk, rst);
input in, clk, rst;
output [1:0] state;
wire a, b;
assign a = state[1];
assign b = state[0];
tff ta((~a&b)|(b&~in), clk, rst, state[1]);
tff tb((~b&~in)|(a&~in)|(~a&b&in), clk, rst, state[0]);
endmodule

sem_3/verilog/lab_08/state2_tb.v
`timescale 1ns/1ns
`include "state2.v"
module state2_tb;
reg in, clk, rst;
wire [1:0] state; 
state2 uut(state, in , clk, rst);
initial begin
    $dumpfile("state2_tb.vcd");
    $dumpvars(0, state2_tb);
    clk = 0; 
    forever #20 clk = ~clk;
end
initial begin
	rst = 1; in = 0; #20;
	rst = 0; in = 1; #20;
	in = 0; #20;
	in = 1; #20;
	in = 0; #20;
	in = 0; #20;
	in = 1; #20;
	in = 0; #20;
	$finish;
end
endmodule

III/verilog/lab_08/state2_tb.vcd
$date
	Sat Nov  4 18:10:41 2023
$end
$version
	Icarus Verilog
$end
$timescale
	1ns
$end
$scope module state2_tb $end
$var wire 2 ! state [1:0] $end
$var reg 1 " clk $end
$var reg 1 # in $end
$var reg 1 $ rst $end
$scope module uut $end
$var wire 1 " clk $end
$var wire 1 # in $end
$var wire 1 $ rst $end
$var wire 2 % state [1:0] $end
$var wire 1 & b $end
$var wire 1 ' a $end
$scope module ta $end
$var wire 1 " clk $end
$var wire 1 $ rst $end
$var wire 1 ( t $end
$var reg 1 ) q $end
$upscope $end
$scope module tb $end
$var wire 1 " clk $end
$var wire 1 $ rst $end
$var wire 1 * t $end
$var reg 1 + q $end
$upscope $end
$upscope $end
$upscope $end
$enddefinitions $end
$comment Show the parameter values. $end
$dumpall
$end
#0
$dumpvars
0+
1*
0)
0(
0'
0&
b0 %
1$
0#
0"
b0 !
$end
#20
1(
1&
b1 !
b1 %
1+
1*
1#
0$
1"
#40
0*
0#
0"
#60
0(
1'
b11 !
b11 %
1)
0*
1#
1"
#80
1*
1(
0#
0"
#100
1*
0(
0&
0'
0+
b0 !
b0 %
0)
1"
#120
0*
1#
0"
#140
1*
0#
1"
