iii/verilog/lab_05/mux4to1.v
module mux4to1(s, w, f);
input [1:0] s;
input [3:0] w;
output reg f;
always @ (s or w) begin
    case (s)
        2'b00: f = w[0];
        2'b01: f = w[1];
        2'b10: f = w[2];
        2'b11: f = w[3];
    endcase
end
endmodule

iii/verilog/lab_05/kmap1.v
`include "mux4to1.v"
module kmap1(a, b, c, d, f);
input a, b, c, d;
output f;
wire [3:0] in;
wire [1:0] sel;
assign in[0] = (~c&d)|(~d);
assign in[1] = ~d;
assign in[2] = ~c&d;
assign in[3] = ~d;
assign sel = {a, b};
mux4to1 mux1(sel, in, f);
endmodule

iii/verilog/lab_05/kmap1_tb.v
`timescale 1ns/1ns
`include "kmap1.v"
module kmap1_tb;
reg a, b, c, d;
wire f;
integer i;
kmap1 uut(a, b, c, d, f);
initial begin
    $dumpfile("kmap1_tb.vcd");
    $dumpvars(0, kmap1_tb);
    for (i = 0; i < 16; i = i + 1) begin
        {a, b, c, d} = i;
        #20;
    end
end
endmodule

III/verilog/lab_05/kmap1_tb.vcd
$date
	Mon Oct  2 13:13:16 2023
$end
$version
	Icarus Verilog
$end
$timescale
	1ns
$end
$scope module kmap1_tb $end
$var wire 1 ! f $end
$var reg 1 " a $end
$var reg 1 # b $end
$var reg 1 $ c $end
$var reg 1 % d $end
$var integer 32 & i [31:0] $end
$scope module uut $end
$var wire 1 " a $end
$var wire 1 # b $end
$var wire 1 $ c $end
$var wire 1 % d $end
$var wire 2 ' sel [1:0] $end
$var wire 4 ( in [3:0] $end
$var wire 1 ! f $end
$scope module mux1 $end
$var wire 2 ) s [1:0] $end
$var wire 4 * w [3:0] $end
$var reg 1 ! f $end
$upscope $end
$upscope $end
$upscope $end
$enddefinitions $end
$comment Show the parameter values. $end
$dumpall
$end
#0
$dumpvars
b1011 *
b0 )
b1011 (
b0 '
b0 &
0%
0$
0#
0"
1!
$end
#20
b101 (
b101 *
1%
b1 &
#40
b1011 (
b1011 *
1$
0%
b10 &
#60
0!
b0 (
b0 *
1%
b11 &
#80
1!
b1011 (
b1011 *
b1 '
b1 )
1#
0$
0%
b100 &
#100
0!
b101 (
b101 *
1%
b101 &
#120
1!
b1011 (
b1011 *
1$
0%
b110 &
#140
0!
b0 (
b0 *
1%
b111 &
#160
b1011 (
b1011 *
1"
b10 '
b10 )
0#
0$
0%
b1000 &
#180
1!
b101 (
b101 *
1%
b1001 &
#200
0!
b1011 (
b1011 *
1$
0%
b1010 &
#220
b0 (
b0 *
1%
b1011 &
#240
1!
b1011 (
b1011 *
b11 '
b11 )
1#
0$
0%
b1100 &
#260
0!
b101 (
b101 *
1%
b1101 &
#280
1!
b1011 (
b1011 *
1$
0%
b1110 &
#300
0!
b0 (
b0 *
1%
b1111 &
#320
b10000 &
