III/verilog/lab_05/decoder4to16.v
module decoder4to16(en, s, w);
input en;
input [3:0] s;
output reg [15:0] w;
integer i;
always @ (en or s) begin
    if (en) begin
        for (i = 0; i < 16; i = i + 1) begin
            if (s == i)
                w[i] = 1;
            else
                w[i] = 0;
        end
    end
    else 
        w[i]=0;
end
endmodule

sem_3/verilog/lab_05/orca.v
`include "decoder4to16.v"
module orca(f, a, b, c, d);
input a, b, c, d;
output f;
wire [15:0] q;
decoder4to16 d1(1'b1, {a, b, c, d}, q);
assign f = q[1]|q[4]|q[6]|q[8]|q[9]|q[13]|q[15];
endmodule

sem_3/verilog/lab_05/orca_tb.v
`timescale 1ns/1ns
`include "orca.v"
module orca_tb;
reg a, b, c, d;
wire f;
integer i;
orca uut(f, a, b, c, d);
initial begin
    $dumpfile("orca_tb.vcd");
    $dumpvars(0, orca_tb);
    for (i = 0; i < 16; i = i + 1) begin
        {a, b, c, d} = i;
        #20;
    end
    $display("test complete");
end
endmodule

iii/verilog/lab_05/orca_tb.vcd
$date
	Sat Oct 14 12:33:27 2023
$end
$version
	Icarus Verilog
$end
$timescale
	1ns
$end
$scope module orca_tb $end
$var wire 1 ! f $end
$var reg 1 " a $end
$var reg 1 # b $end
$var reg 1 $ c $end
$var reg 1 % d $end
$var integer 32 & i [31:0] $end
$scope module uut $end
$var wire 1 " a $end
$var wire 1 # b $end
$var wire 1 $ c $end
$var wire 1 % d $end
$var wire 1 ! f $end
$var wire 16 ' q [15:0] $end
$scope module d1 $end
$var wire 1 ( en $end
$var wire 4 ) s [3:0] $end
$var reg 16 * w [15:0] $end
$var integer 32 + i [31:0] $end
$upscope $end
$upscope $end
$upscope $end
$enddefinitions $end
$comment Show the parameter values. $end
$dumpall
$end
#0
$dumpvars
b10000 +
b1 *
b0 )
1(
b1 '
b0 &
0%
0$
0#
0"
0!
$end
#20
1!
b10 '
b10 *
b10000 +
b1 )
1%
b1 &
#40
0!
b100 '
b100 *
b10000 +
1$
b10 )
0%
b10 &
#60
b1000 '
b1000 *
b10000 +
b11 )
1%
b11 &
#80
1!
b10000 '
b10000 *
b10000 +
1#
0$
b100 )
0%
b100 &
#100
0!
b100000 '
b100000 *
b10000 +
b101 )
1%
b101 &
#120
1!
b1000000 '
b1000000 *
b10000 +
1$
b110 )
0%
b110 &
#140
0!
b10000000 '
b10000000 *
b10000 +
b111 )
1%
b111 &
#160
1!
b100000000 '
b100000000 *
b10000 +
1"
0#
0$
b1000 )
0%
b1000 &
#180
b1000000000 '
b1000000000 *
b10000 +
b1001 )
1%
b1001 &
#200
0!
b10000000000 '
b10000000000 *
b10000 +
1$
b1010 )
0%
b1010 &
#220
b100000000000 '
b100000000000 *
b10000 +
b1011 )
1%
b1011 &
#240
b1000000000000 '
b1000000000000 *
b10000 +
1#
0$
b1100 )
0%
b1100 &
#260
1!
b10000000000000 '
b10000000000000 *
b10000 +
b1101 )
1%
b1101 &
#280
0!
b100000000000000 '
b100000000000000 *
b10000 +
1$
b1110 )
0%
b1110 &
#300
1!
b1000000000000000 '
b1000000000000000 *
b10000 +
b1111 )
1%
b1111 &
#320
b10000 &
