sem_3/verilog/lab_10/jkff.v
module jkff(j, k, clk, rst, q);
input j, k, clk, rst;
output reg q;
always @ (posedge clk or posedge rst) begin
    if (rst) 
        q <= 0;
    else
        case ({j, k})
            2'b00: q <= q;
            2'b01: q <= 0;
            2'b10: q <= 1;
            2'b11: q <= ~q;
        endcase
end
endmodule

sem_3/verilog/lab_10/seq1.v
`include "jkff.v"
module seq1(clk, rst, out);
input clk, rst;
output [3:1] out;
assign b3 = out[3];
assign b2 = out[2];
assign b1 = out[1];
jkff j3(b2, b2&b1, clk, rst, out[3]);
jkff j2(b1, ~b3|b1, clk, rst, out[2]);
jkff j1(~b2|b3, 1'b1, clk, rst, out[1]);
endmodule

iii/verilog/lab_10/seq1_tb.v
`timescale 1ns/1ns
`include "seq1.v"
module seq1_tb;
reg rst, clk;
wire [3:1] out; 
seq1 uut(clk, rst, out);
initial begin
    $dumpfile("seq1_tb.vcd");
    $dumpvars(0, seq1_tb);
    clk = 0; 
    forever #20 clk = ~clk;
end
initial begin
	rst = 0; #20;
	rst = 1; #20;
	rst = 0; #360;
	$finish;
end
endmodule

sem_3/verilog/lab_10/seq1_tb.vcd
$date
	Sat Nov  4 18:11:58 2023
$end
$version
	Icarus Verilog
$end
$timescale
	1ns
$end
$scope module seq1_tb $end
$var wire 3 ! out [3:1] $end
$var reg 1 " clk $end
$var reg 1 # rst $end
$scope module uut $end
$var wire 1 " clk $end
$var wire 1 # rst $end
$var wire 3 $ out [3:1] $end
$var wire 1 % b3 $end
$var wire 1 & b2 $end
$var wire 1 ' b1 $end
$scope module j1 $end
$var wire 1 " clk $end
$var wire 1 ( j $end
$var wire 1 ) k $end
$var wire 1 # rst $end
$var reg 1 * q $end
$upscope $end
$scope module j2 $end
$var wire 1 " clk $end
$var wire 1 ' j $end
$var wire 1 + k $end
$var wire 1 # rst $end
$var reg 1 , q $end
$upscope $end
$scope module j3 $end
$var wire 1 " clk $end
$var wire 1 & j $end
$var wire 1 - k $end
$var wire 1 # rst $end
$var reg 1 . q $end
$upscope $end
$upscope $end
$upscope $end
$enddefinitions $end
$comment Show the parameter values. $end
$dumpall
$end
#0
$dumpvars
x.
x-
x,
x+
x*
1)
x(
x'
x&
x%
bx $
0#
0"
bx !
$end
#20
1+
1(
0-
0%
0&
0'
0.
0,
b0 !
b0 $
0*
1#
1"
#40
0#
0"
#60
1'
b1 !
b1 $
1*
1"
#80
0"
#100
0(
1&
0'
1,
b10 !
b10 $
0*
1"
#120
0"
#140
0+
1(
0&
1%
0,
b100 !
b100 $
1.
1"
#160
0"
#180
1+
1'
b101 !
b101 $
1*
1"
#200
0"
#220
0+
0'
1&
0*
b110 !
b110 $
1,
1"
#240
0"
#260
1+
1-
1'
b111 !
b111 $
1*
1"
#280
0"
#300
0-
1(
0'
0&
0%
0*
0,
b0 !
b0 $
0.
1"
#320
0"
#340
1'
b1 !
b1 $
1*
1"
#360
0"
#380
0(
0'
1&
0*
b10 !
b10 $
1,
1"
