sem_3/verilog/lab_10/tff.v
module tff(t, clk, rst, q);
input t, clk, rst;
output reg q;
always @ (posedge clk or posedge rst) begin
    if (rst)
        q <= 0;
    else 
        if (t)
            q <= ~q;
        else 
            q <= q;
end
endmodule

iii/verilog/lab_10/seq3.v
`include "tff.v"
module seq3(clk, rst, out);
input clk, rst;
output [3:1] out;
assign b3 = out[3];
assign b2 = out[2];
assign b1 = out[1];
tff t3(b3^b2, clk, rst, out[3]);
tff t2(b1^b2, clk, rst, out[2]);
tff t1(~(b3^b1), clk, rst, out[1]);
endmodule

iii/verilog/lab_10/seq3_tb.v
`timescale 1ns/1ns
`include "seq3.v"
module seq3_tb;
reg rst, clk;
wire [3:1] out; 
seq3 uut(clk, rst, out);
initial begin
    $dumpfile("seq3_tb.vcd");
    $dumpvars(0, seq3_tb);
    clk = 0; 
    forever #20 clk = ~clk;
end
initial begin
	rst = 0; #20;
	rst = 1; #20;
	rst = 0; #360;
	$finish;
end
endmodule

sem_3/verilog/lab_10/seq3_tb.vcd
$date
	Sat Nov  4 18:11:56 2023
$end
$version
	Icarus Verilog
$end
$timescale
	1ns
$end
$scope module seq3_tb $end
$var wire 3 ! out [3:1] $end
$var reg 1 " clk $end
$var reg 1 # rst $end
$scope module uut $end
$var wire 1 " clk $end
$var wire 1 # rst $end
$var wire 3 $ out [3:1] $end
$var wire 1 % b3 $end
$var wire 1 & b2 $end
$var wire 1 ' b1 $end
$scope module t1 $end
$var wire 1 " clk $end
$var wire 1 # rst $end
$var wire 1 ( t $end
$var reg 1 ) q $end
$upscope $end
$scope module t2 $end
$var wire 1 " clk $end
$var wire 1 # rst $end
$var wire 1 * t $end
$var reg 1 + q $end
$upscope $end
$scope module t3 $end
$var wire 1 " clk $end
$var wire 1 # rst $end
$var wire 1 , t $end
$var reg 1 - q $end
$upscope $end
$upscope $end
$upscope $end
$enddefinitions $end
$comment Show the parameter values. $end
$dumpall
$end
#0
$dumpvars
x-
x,
x+
x*
x)
x(
x'
x&
x%
bx $
0#
0"
bx !
$end
#20
1(
0,
0*
0%
0&
0'
0-
0+
b0 !
b0 $
0)
1#
1"
#40
0#
0"
#60
0(
1*
1'
b1 !
b1 $
1)
1"
#80
0"
#100
0*
1,
1&
b11 !
b11 $
1+
1"
#120
0"
#140
1(
0,
1%
b111 !
b111 $
1-
1"
#160
0"
#180
0(
1*
0'
b110 !
b110 $
0)
1"
#200
0"
#220
0*
1,
0&
b100 !
b100 $
0+
1"
#240
0"
#260
1(
0,
0%
b0 !
b0 $
0-
1"
#280
0"
#300
0(
1*
1'
b1 !
b1 $
1)
1"
#320
0"
#340
0*
1,
1&
b11 !
b11 $
1+
1"
#360
0"
#380
1(
0,
1%
b111 !
b111 $
1-
1"
