iii/verilog/lab_10/srff.v
module srff(s, r, clk, rst, q);
input s, r, clk, rst;
output reg q;
always @ (posedge clk or posedge rst) begin
    if (rst) 
        q <= 0;
    else
        case ({s, r})
            2'b00: q <= q;
            2'b01: q <= 0;
            2'b10: q <= 1;
            2'b11: q <= 1'bx;
        endcase
end
endmodule

iii/verilog/lab_10/seq2.v
`include "srff.v"
module seq2(clk, rst, out);
input clk, rst;
output [3:1] out;
assign b3 = out[3];
assign b2 = out[2];
assign b1 = out[1];
srff s3(~b2&~b1, ~b2&b1, clk, rst, out[3]);
srff s2(~b3&~b2, (b3&~b1)|(~b3&b2&b1),clk, rst, out[2]);
srff s1(~b1, (~b3&b1)|(b2&b1),clk, rst, out[1]);
endmodule

iii/verilog/lab_10/seq2_tb.v
`timescale 1ns/1ns
`include "seq2.v"
module seq2_tb;
reg rst, clk;
wire [3:1] out; 
seq2 uut(clk, rst, out);
initial begin
    $dumpfile("seq2_tb.vcd");
    $dumpvars(0, seq2_tb);
    clk = 0; 
    forever #20 clk = ~clk;
end
initial begin
	rst = 0; #20;
	rst = 1; #20;
	rst = 0; #360;
	$finish;
end
endmodule

iii/verilog/lab_10/seq2_tb.vcd
$date
	Sat Nov  4 18:11:59 2023
$end
$version
	Icarus Verilog
$end
$timescale
	1ns
$end
$scope module seq2_tb $end
$var wire 3 ! out [3:1] $end
$var reg 1 " clk $end
$var reg 1 # rst $end
$scope module uut $end
$var wire 1 " clk $end
$var wire 1 # rst $end
$var wire 3 $ out [3:1] $end
$var wire 1 % b3 $end
$var wire 1 & b2 $end
$var wire 1 ' b1 $end
$scope module s1 $end
$var wire 1 " clk $end
$var wire 1 ( r $end
$var wire 1 # rst $end
$var wire 1 ) s $end
$var reg 1 * q $end
$upscope $end
$scope module s2 $end
$var wire 1 " clk $end
$var wire 1 + r $end
$var wire 1 # rst $end
$var wire 1 , s $end
$var reg 1 - q $end
$upscope $end
$scope module s3 $end
$var wire 1 " clk $end
$var wire 1 . r $end
$var wire 1 # rst $end
$var wire 1 / s $end
$var reg 1 0 q $end
$upscope $end
$upscope $end
$upscope $end
$enddefinitions $end
$comment Show the parameter values. $end
$dumpall
$end
#0
$dumpvars
x0
x/
x.
x-
x,
x+
x*
x)
x(
x'
x&
x%
bx $
0#
0"
bx !
$end
#20
1,
0(
0+
1/
1)
0.
0%
0&
0'
00
0-
b0 !
b0 $
0*
1#
1"
#40
0#
0"
#60
1(
0/
0+
0,
0)
1'
1&
1%
1*
1-
b111 !
b111 $
10
1"
#80
0"
#100
1+
0(
1)
0'
b110 !
b110 $
0*
1"
#120
0"
#140
0+
0)
1.
1'
0&
1*
b101 !
b101 $
0-
1"
#160
0"
#180
1(
1,
0%
b1 !
b1 $
00
1"
#200
0"
#220
0(
0,
1)
0.
0'
1&
0*
b10 !
b10 $
1-
1"
#240
0"
#260
1(
1+
0)
1'
b11 !
b11 $
1*
1"
#280
0"
#300
0+
0(
1,
1/
1)
0'
0&
0*
b0 !
b0 $
0-
1"
#320
0"
#340
0+
0,
1(
0/
0)
0.
1%
1&
1'
10
1-
b111 !
b111 $
1*
1"
#360
0"
#380
1+
0(
1)
0'
b110 !
b110 $
0*
1"
